gensbi/__init__.py
gensbi/diagnostics/__init__.py
gensbi/diagnostics/distribution_wrapper.py
gensbi/diagnostics/lc2st.py
gensbi/diagnostics/sbc.py
gensbi/diagnostics/tarp.py
gensbi/diagnostics/metrics/__init__.py
gensbi/diagnostics/metrics/c2st.py
gensbi/diagnostics/metrics/l1_l2.py
gensbi/diffusion/__init__.py
gensbi/diffusion/path/__init__.py
gensbi/diffusion/path/edm_path.py
gensbi/diffusion/path/path.py
gensbi/diffusion/path/path_sample.py
gensbi/diffusion/path/scheduler/__init__.py
gensbi/diffusion/path/scheduler/edm.py
gensbi/diffusion/solver/__init__.py
gensbi/diffusion/solver/edm_samplers.py
gensbi/diffusion/solver/sde_solver.py
gensbi/diffusion/solver/solver.py
gensbi/experimental/__init__.py
gensbi/experimental/models/__init__.py
gensbi/experimental/models/autoencoders/__init__.py
gensbi/experimental/models/autoencoders/autoencoder_1d.py
gensbi/experimental/models/autoencoders/autoencoder_2d.py
gensbi/experimental/models/autoencoders/commons.py
gensbi/experimental/recipes/__init__.py
gensbi/experimental/recipes/latent_conditional_pipeline.py.off
gensbi/experimental/recipes/latent_flux1.py.off
gensbi/experimental/recipes/vae_pipeline.py
gensbi/flow_matching/README
gensbi/flow_matching/__init__.py
gensbi/flow_matching/loss/__init__.py
gensbi/flow_matching/loss/continuous_loss.py
gensbi/flow_matching/path/__init__.py
gensbi/flow_matching/path/affine.py
gensbi/flow_matching/path/path.py
gensbi/flow_matching/path/path_sample.py
gensbi/flow_matching/path/scheduler/__init__.py
gensbi/flow_matching/path/scheduler/schedule_transform.py
gensbi/flow_matching/path/scheduler/scheduler.py
gensbi/flow_matching/solver/__init__.py
gensbi/flow_matching/solver/ode_solver.py
gensbi/flow_matching/solver/sde_solver.py.bk
gensbi/flow_matching/solver/solver.py
gensbi/flow_matching/utils/__init__.py
gensbi/flow_matching/utils/utils.py
gensbi/models/__init__.py
gensbi/models/embedding/__init__.py
gensbi/models/embedding/embedding.py
gensbi/models/flux1/__init__.py
gensbi-0.0.2.dist-info/METADATA
gensbi-0.0.2.dist-info/WHEEL
gensbi-0.0.2.dist-info/licenses/LICENSE
gensbi-0.0.2.dist-info/RECORD
