Metadata-Version: 2.4
Name: gensbi
Version: 0.0.2
Summary: GenSBI is a library for Simulation-Based Inference using generative models in JAX.
Project-URL: Homepage, https://github.com/aurelio-amerio/GenSBI
Project-URL: Issues, https://github.com/aurelio-amerio/GenSBI/issues
Author-email: Aurelio Amerio <aure.amerio@gmail.com>
License:    Copyright 2025 Amerio Aurelio
License-File: LICENSE
Requires-Python: >=3.11
Requires-Dist: corner>=2.2.3
Requires-Dist: diffrax>=0.7.0
Requires-Dist: einops>=0.8.1
Requires-Dist: equinox>=0.13.1
Requires-Dist: flax>=0.12.0
Requires-Dist: grain>=0.2.12
Requires-Dist: jax<=0.8.1,>=0.7.2
Requires-Dist: matplotlib>=3.10
Requires-Dist: numpy>=2.0
Requires-Dist: numpyro>=0.19.0
Requires-Dist: optax>=0.2.6
Requires-Dist: orbax-checkpoint>=0.11.25
Requires-Dist: scikit-learn>=1.7.0
Requires-Dist: scipy>=1.16.0
Requires-Dist: seaborn>=0.13.2
Requires-Dist: tqdm>=4.62.0
Provides-Extra: cuda12
Requires-Dist: jax[cuda12]<=0.8.1,>=0.7.2; extra == 'cuda12'
Provides-Extra: docs
Requires-Dist: ablog>=0.11.8; extra == 'docs'
Requires-Dist: astroid<5,>=3; extra == 'docs'
Requires-Dist: colorama; extra == 'docs'
Requires-Dist: graphviz; extra == 'docs'
Requires-Dist: ipykernel; extra == 'docs'
Requires-Dist: ipyleaflet; extra == 'docs'
Requires-Dist: ipywidgets; extra == 'docs'
Requires-Dist: jupyter-sphinx; extra == 'docs'
Requires-Dist: jupyterlite-sphinx; extra == 'docs'
Requires-Dist: linkify-it-py; extra == 'docs'
Requires-Dist: matplotlib; extra == 'docs'
Requires-Dist: myst-parser; extra == 'docs'
Requires-Dist: nbsphinx; extra == 'docs'
Requires-Dist: numpy; extra == 'docs'
Requires-Dist: numpydoc; extra == 'docs'
Requires-Dist: pandas; extra == 'docs'
Requires-Dist: pandoc; extra == 'docs'
Requires-Dist: plotly; extra == 'docs'
Requires-Dist: pydata-sphinx-theme; extra == 'docs'
Requires-Dist: rich; extra == 'docs'
Requires-Dist: sphinx; extra == 'docs'
Requires-Dist: sphinx-autoapi>=3.0.0; extra == 'docs'
Requires-Dist: sphinx-copybutton; extra == 'docs'
Requires-Dist: sphinx-design; extra == 'docs'
Requires-Dist: sphinx-favicon>=1.0.1; extra == 'docs'
Requires-Dist: sphinx-sitemap<2.7.0; extra == 'docs'
Requires-Dist: sphinx-togglebutton; extra == 'docs'
Requires-Dist: sphinxcontrib-mermaid; extra == 'docs'
Requires-Dist: sphinxcontrib-youtube>=1.4.1; extra == 'docs'
Requires-Dist: sphinxext-rediraffe; extra == 'docs'
Requires-Dist: xarray; extra == 'docs'
Provides-Extra: examples
Requires-Dist: gensbi-examples; extra == 'examples'
Provides-Extra: test
Requires-Dist: flake8; extra == 'test'
Requires-Dist: genbadge[all]; extra == 'test'
Requires-Dist: pytest; extra == 'test'
Requires-Dist: pytest-cov; extra == 'test'
Requires-Dist: pytest-env; extra == 'test'
Requires-Dist: pytest-mock; extra == 'test'
Requires-Dist: pytest-xdist; extra == 'test'
Provides-Extra: tpu
Requires-Dist: jax[tpu]<=0.8.1,>=0.7.2; extra == 'tpu'
